<?xml version='1.0' encoding='utf-8'?>
<Gesture Name="U18" Subject="0" Speed="medium" Number="18" NumPts="33" Millseconds="2208" AppName="emmas_app" AppVer="1.0" Date="Wednesday, June 19, 2024" TimeOfDay="12:09:54 PM"><Point X="113" Y="105" T="1718791791.840578" /><Point X="113" Y="105" T="17" /><Point X="113" Y="108" T="91" /><Point X="115" Y="124" T="150" /><Point X="117" Y="139" T="217" /><Point X="117" Y="165" T="283" /><Point X="112" Y="189" T="343" /><Point X="107" Y="228" T="411" /><Point X="104" Y="259" T="478" /><Point X="104" Y="276" T="534" /><Point X="104" Y="304" T="614" /><Point X="104" Y="329" T="667" /><Point X="104" Y="343" T="750" /><Point X="104" Y="352" T="816" /><Point X="103" Y="374" T="885" /><Point X="104" Y="394" T="952" /><Point X="109" Y="419" T="999" /><Point X="117" Y="434" T="1067" /><Point X="137" Y="455" T="1154" /><Point X="156" Y="464" T="1220" /><Point X="182" Y="467" T="1266" /><Point X="216" Y="450" T="1333" /><Point X="240" Y="420" T="1400" /><Point X="258" Y="391" T="1492" /><Point X="272" Y="353" T="1560" /><Point X="280" Y="306" T="1627" /><Point X="287" Y="259" T="1667" /><Point X="294" Y="212" T="1733" /><Point X="295" Y="182" T="1817" /><Point X="294" Y="160" T="1933" /><Point X="293" Y="148" T="2084" /><Point X="293" Y="148" T="2152" /><Point X="293" Y="148" T="2207" /></Gesture>